Metadata-Version: 2.1
Name: Mensajes-Crackbana
Version: 6.0
Summary: Un paquete para saludar y despedir
Home-page: https://www.hektor.dev
Author: Jesús Cabana
Author-email: jesuscabana111@gmail.com
Classifier: Environment :: Web Environment
Classifier: License :: Free For Home Use
Classifier: Natural Language :: English
Classifier: Operating System :: Microsoft
Classifier: Programming Language :: Python :: 3.9
Classifier: Topic :: Database
License-File: LICENSE
Requires-Dist: numpy (>=1.23.1)
